weather/__init__.py
weather/__main__.py
weather/server.py
rents_mcp_weather2-0.1.0.dist-info/METADATA
rents_mcp_weather2-0.1.0.dist-info/WHEEL
rents_mcp_weather2-0.1.0.dist-info/entry_points.txt
rents_mcp_weather2-0.1.0.dist-info/top_level.txt
rents_mcp_weather2-0.1.0.dist-info/RECORD
