Metadata-Version: 2.4
Name: rents-mcp-weather2
Version: 0.1.0
Summary: Rentaoshu's test MCP weather server.
Requires-Python: >=3.10
Requires-Dist: dotenv>=0.9.9
Requires-Dist: mcp>=1.18.0
Requires-Dist: openai>=2.5.0
